{
  "generated_at": "2026-06-25T11:00:28+08:00",
  "checked_at": "2026-06-25T11:00:28+08:00",
  "data_updated_at": "2026-06-25 11:00:28",
  "source_status": "live",
  "is_market_open": true,
  "etfs": [
    {
      "code": "513100",
      "name": "纳指 ETF",
      "price": 2.193,
      "iopv": 1.9883,
      "premium_pct": 10.3,
      "updated": "2026-06-25 11:00:28",
      "signal": "danger"
    },
    {
      "code": "513500",
      "name": "标普 ETF",
      "price": 2.51,
      "iopv": 2.3742,
      "premium_pct": 5.72,
      "updated": "2026-06-25 11:00:28",
      "signal": "caution"
    },
    {
      "code": "513180",
      "name": "恒生科技 ETF",
      "price": 0.56,
      "iopv": 0.5622,
      "premium_pct": -0.39,
      "updated": "2026-06-25 11:00:28",
      "signal": "safe"
    },
    {
      "code": "513880",
      "name": "日经225 ETF",
      "price": 2.398,
      "iopv": 2.203,
      "premium_pct": 8.85,
      "updated": "2026-06-25 11:00:28",
      "signal": "caution"
    },
    {
      "code": "518880",
      "name": "黄金 ETF",
      "price": 8.302,
      "iopv": 8.2952,
      "premium_pct": 0.08,
      "updated": "2026-06-25 11:00:28",
      "signal": "neutral"
    }
  ],
  "southbound": {
    "net_buy": 15.92,
    "updated": "2026-06-25 11:00:28"
  }
}